ordeq/__init__.py
ordeq/_async.py
ordeq/_catalog.py
ordeq/_fqn.py
ordeq/_graph.py
ordeq/_hook.py
ordeq/_io.py
ordeq/_nodes.py
ordeq/_patch.py
ordeq/_pipeline.py
ordeq/_process_ios.py
ordeq/_process_nodes.py
ordeq/_process_nodes_and_ios.py
ordeq/_resolve.py
ordeq/_resource.py
ordeq/_runner.py
ordeq/_scan.py
ordeq/_static.py
ordeq/_substitute.py
ordeq/_version.py
ordeq/preview.py
ordeq/py.typed
ordeq/types.py
ordeq-1.4.2.dist-info/licenses/LICENSE
ordeq-1.4.2.dist-info/METADATA
ordeq-1.4.2.dist-info/WHEEL
ordeq-1.4.2.dist-info/top_level.txt
ordeq-1.4.2.dist-info/RECORD
