Metadata-Version: 2.4
Name: ordeq
Version: 1.4.2
Summary: Ordeq is a framework that simplifies IO and modularizes pipeline logic
Author: Niels Neerhoff, Simon Brugman
Maintainer: Niels Neerhoff, Simon Brugman
License-Expression: MIT
Requires-Python: >=3.10
License-File: LICENSE
Dynamic: license-file
